aws_fuzzy/VERSION
aws_fuzzy/__init__.py
aws_fuzzy/cli.py
aws_fuzzy/common.py
aws_fuzzy/query.py
aws_fuzzy/commands/__init__.py
aws_fuzzy/commands/cmd_inventory.py
aws_fuzzy/commands/cmd_plot.py
aws_fuzzy/commands/cmd_ssh.py
aws_fuzzy/commands/cmd_sso.py
aws_fuzzy-0.6.8.dist-info/LICENSE
aws_fuzzy-0.6.8.dist-info/METADATA
aws_fuzzy-0.6.8.dist-info/WHEEL
aws_fuzzy-0.6.8.dist-info/entry_points.txt
aws_fuzzy-0.6.8.dist-info/top_level.txt
aws_fuzzy-0.6.8.dist-info/RECORD
