Metadata-Version: 2.1
Name: aws-fuzzy
Version: 0.6.8
Summary: UNKNOWN
Home-page: UNKNOWN
License: UNKNOWN
Platform: UNKNOWN
Requires-Python: >=3
Requires-Dist: click
Requires-Dist: boto3 (>=1.12)
Requires-Dist: botocore (>=1.15)
Requires-Dist: pygments
Requires-Dist: iterfzf
Requires-Dist: pyvis
